{
  "parser_version": "0.1.0",
  "id": "CATASTROPHE",
  "class_name": "Catastrophe",
  "name": "Catastrophe",
  "file": "Lab/decompiled/v0.103.2/MegaCrit.Sts2.Core.Models.Cards/Catastrophe.cs",
  "cost": 2,
  "type": "Skill",
  "rarity": "Uncommon",
  "target": "Self",
  "localization": {
    "title_key": "CATASTROPHE.title",
    "description_key": "CATASTROPHE.description",
    "title": null,
    "description_raw": null
  },
  "vars": {
    "Cards": 2
  },
  "keywords": [
    "Unplayable"
  ],
  "tags": [],
  "upgrades": [
    {
      "var": "Cards",
      "delta": 1
    }
  ],
  "applies_powers": [],
  "relations": [],
  "notes": [
    "Description is not present in the C# file; supply localization data to populate it."
  ]
}
