{
  "schema_version": "0.2.1",
  "id": "FTL",
  "raw": {
    "parser_version": "0.2.1",
    "class_name": "Ftl",
    "file": "Lab/decompiled/v0.103.2/MegaCrit.Sts2.Core.Models.Cards/Ftl.cs",
    "cost": 0,
    "type": "Attack",
    "rarity": "Uncommon",
    "target": "AnyEnemy",
    "localization": {
      "table": "cards",
      "title_key": "FTL.title",
      "description_key": "FTL.description"
    },
    "vars": {
      "Damage": 5,
      "Cards": 1
    },
    "assets": [
      {
        "kind": "portrait",
        "path": "Lab/resources/images/packed/card_portraits/defect/ftl.webp",
        "source": "Lab.resources.images.packed.card_portraits"
      }
    ],
    "upgrades": [
      {
        "var": "Damage",
        "delta": 1
      },
      {
        "var": "PlayMax",
        "delta": 1
      }
    ]
  },
  "resolved": {
    "base": {
      "title": "FTL",
      "cost": 0,
      "description": {
        "plain": "Deal 5 damage.\nIf you have played fewer than {PlayMax:diff()} cards this turn, draw 1 card.",
        "runs": [
          {
            "text": "Deal "
          },
          {
            "text": "5",
            "source_var": "Damage"
          },
          {
            "text": " damage.\nIf you have played fewer than {PlayMax:diff()} cards this turn, draw 1 card."
          }
        ]
      }
    },
    "upgraded": {
      "title": "FTL+",
      "cost": 0,
      "description": {
        "plain": "Deal 6 damage.\nIf you have played fewer than {PlayMax:diff()} cards this turn, draw 1 card.",
        "runs": [
          {
            "text": "Deal "
          },
          {
            "text": "6",
            "source_var": "Damage",
            "style": "green"
          },
          {
            "text": " damage.\nIf you have played fewer than {PlayMax:diff()} cards this turn, draw 1 card."
          }
        ]
      },
      "changed": [
        "description"
      ]
    }
  }
}
