{
  "schema_version": "0.2.3",
  "id": "MEMENTO_MORI",
  "raw": {
    "parser_version": "0.2.3",
    "class_name": "MementoMori",
    "file": "Lab/decompiled/v0.103.2/MegaCrit.Sts2.Core.Models.Cards/MementoMori.cs",
    "cost": 1,
    "energy_cost": {
      "kind": "int",
      "value": 1
    },
    "type": "Attack",
    "rarity": "Uncommon",
    "target": "AnyEnemy",
    "card_pool": "silent",
    "localization": {
      "table": "cards",
      "title_key": "MEMENTO_MORI.title",
      "description_key": "MEMENTO_MORI.description"
    },
    "vars": {
      "CalculationBase": 9,
      "ExtraDamage": 4
    },
    "assets": [
      {
        "kind": "portrait",
        "path": "Lab/resources/images/packed/card_portraits/silent/memento_mori.webp",
        "source": "Lab.resources.images.packed.card_portraits"
      }
    ],
    "upgrades": [
      {
        "var": "CalculationBase",
        "delta": 2
      },
      {
        "var": "ExtraDamage",
        "delta": 1
      }
    ]
  },
  "resolved": {
    "base": {
      "title": "Memento Mori",
      "cost": 1,
      "energy_cost": {
        "kind": "int",
        "value": 1
      },
      "description": {
        "plain": "Deal {CalculatedDamage:diff()} damage.\nDeals 4 additional damage for each card discarded this turn.",
        "runs": [
          {
            "text": "Deal {CalculatedDamage:diff()} damage.\nDeals "
          },
          {
            "text": "4",
            "source_var": "ExtraDamage"
          },
          {
            "text": " additional damage for each card discarded this turn."
          }
        ]
      }
    },
    "upgraded": {
      "title": "Memento Mori+",
      "cost": 1,
      "energy_cost": {
        "kind": "int",
        "value": 1
      },
      "description": {
        "plain": "Deal {CalculatedDamage:diff()} damage.\nDeals 5 additional damage for each card discarded this turn.",
        "runs": [
          {
            "text": "Deal {CalculatedDamage:diff()} damage.\nDeals "
          },
          {
            "text": "5",
            "source_var": "ExtraDamage",
            "style": "green"
          },
          {
            "text": " additional damage for each card discarded this turn."
          }
        ]
      },
      "changed": [
        "description"
      ]
    }
  }
}
