{
  "schema_version": "0.2.3",
  "id": "MURDER",
  "raw": {
    "parser_version": "0.2.3",
    "class_name": "Murder",
    "file": "Lab/decompiled/v0.103.2/MegaCrit.Sts2.Core.Models.Cards/Murder.cs",
    "cost": 3,
    "energy_cost": {
      "kind": "int",
      "value": 3
    },
    "type": "Attack",
    "rarity": "Rare",
    "target": "AnyEnemy",
    "card_pool": "silent",
    "localization": {
      "table": "cards",
      "title_key": "MURDER.title",
      "description_key": "MURDER.description"
    },
    "vars": {
      "CalculationBase": 1,
      "ExtraDamage": 1,
      "CalculatedDamage": 1
    },
    "assets": [
      {
        "kind": "portrait",
        "path": "Lab/resources/images/packed/card_portraits/silent/murder.webp",
        "source": "Lab.resources.images.packed.card_portraits"
      },
      {
        "kind": "beta_portrait",
        "path": "Lab/resources/images/packed/card_portraits/silent/beta/murder.webp",
        "source": "Lab.resources.images.packed.card_portraits"
      }
    ],
    "cost_upgrades": [
      {
        "target": "cost",
        "delta": -1,
        "source": "EnergyCost.UpgradeBy"
      }
    ]
  },
  "resolved": {
    "base": {
      "title": "Murder",
      "cost": 3,
      "energy_cost": {
        "kind": "int",
        "value": 3
      },
      "description": {
        "plain": "Deal 1 damage.\nDeals 1 additional damage for each card drawn this combat.",
        "runs": [
          {
            "text": "Deal "
          },
          {
            "text": "1",
            "source_var": "CalculatedDamage"
          },
          {
            "text": " damage.\nDeals "
          },
          {
            "text": "1",
            "source_var": "ExtraDamage"
          },
          {
            "text": " additional damage for each card drawn this combat."
          }
        ]
      }
    },
    "upgraded": {
      "title": "Murder+",
      "cost": 2,
      "energy_cost": {
        "kind": "int",
        "value": 2
      },
      "description": {
        "plain": "Deal 1 damage.\nDeals 1 additional damage for each card drawn this combat.",
        "runs": [
          {
            "text": "Deal "
          },
          {
            "text": "1",
            "source_var": "CalculatedDamage"
          },
          {
            "text": " damage.\nDeals "
          },
          {
            "text": "1",
            "source_var": "ExtraDamage"
          },
          {
            "text": " additional damage for each card drawn this combat."
          }
        ]
      },
      "changed": [
        "cost"
      ]
    }
  }
}
