{
  "parser_version": "0.1.0",
  "id": "POKE",
  "class_name": "Poke",
  "name": "Poke",
  "file": "Lab/decompiled/v0.103.2/MegaCrit.Sts2.Core.Models.Cards/Poke.cs",
  "cost": 0,
  "type": "Attack",
  "rarity": "Common",
  "target": "AnyEnemy",
  "localization": {
    "title_key": "POKE.title",
    "description_key": "POKE.description",
    "title": null,
    "description_raw": null
  },
  "vars": {},
  "keywords": [],
  "tags": [
    "OstyAttack"
  ],
  "upgrades": [
    {
      "var": "OstyDamage",
      "delta": 3
    }
  ],
  "applies_powers": [],
  "relations": [],
  "notes": [
    "Description is not present in the C# file; supply localization data to populate it."
  ]
}
