{
  "parser_version": "0.1.0",
  "id": "REBOOT",
  "class_name": "Reboot",
  "name": "Reboot",
  "file": "Lab/decompiled/v0.103.2/MegaCrit.Sts2.Core.Models.Cards/Reboot.cs",
  "cost": 0,
  "type": "Skill",
  "rarity": "Rare",
  "target": "Self",
  "localization": {
    "title_key": "REBOOT.title",
    "description_key": "REBOOT.description",
    "title": null,
    "description_raw": null
  },
  "vars": {
    "Cards": 4
  },
  "keywords": [
    "Exhaust"
  ],
  "tags": [],
  "upgrades": [
    {
      "var": "Cards",
      "delta": 2
    }
  ],
  "applies_powers": [],
  "relations": [],
  "notes": [
    "Description is not present in the C# file; supply localization data to populate it."
  ]
}
