{
  "schema_version": "0.2.2",
  "id": "ULTIMATE_STRIKE",
  "raw": {
    "parser_version": "0.2.2",
    "class_name": "UltimateStrike",
    "file": "Lab/decompiled/v0.103.2/MegaCrit.Sts2.Core.Models.Cards/UltimateStrike.cs",
    "cost": 1,
    "type": "Attack",
    "rarity": "Uncommon",
    "target": "AnyEnemy",
    "localization": {
      "table": "cards",
      "title_key": "ULTIMATE_STRIKE.title",
      "description_key": "ULTIMATE_STRIKE.description"
    },
    "vars": {
      "Damage": 14
    },
    "assets": [
      {
        "kind": "portrait",
        "path": "Lab/resources/images/packed/card_portraits/colorless/ultimate_strike.webp",
        "source": "Lab.resources.images.packed.card_portraits"
      },
      {
        "kind": "beta_portrait",
        "path": "Lab/resources/images/packed/card_portraits/colorless/beta/ultimate_strike.webp",
        "source": "Lab.resources.images.packed.card_portraits"
      }
    ],
    "tags": [
      "Strike"
    ],
    "upgrades": [
      {
        "var": "Damage",
        "delta": 6
      }
    ]
  },
  "resolved": {
    "base": {
      "title": "Ultimate Strike",
      "cost": 1,
      "description": {
        "plain": "Deal 14 damage.",
        "runs": [
          {
            "text": "Deal "
          },
          {
            "text": "14",
            "source_var": "Damage"
          },
          {
            "text": " damage."
          }
        ]
      }
    },
    "upgraded": {
      "title": "Ultimate Strike+",
      "cost": 1,
      "description": {
        "plain": "Deal 20 damage.",
        "runs": [
          {
            "text": "Deal "
          },
          {
            "text": "20",
            "source_var": "Damage",
            "style": "green"
          },
          {
            "text": " damage."
          }
        ]
      },
      "changed": [
        "description"
      ]
    }
  }
}
